veritensor/__init__.py
veritensor/__main__.py
veritensor/cli/__init__.py
veritensor/cli/main.py
veritensor/core/__init__.py
veritensor/core/cache.py
veritensor/core/config.py
veritensor/core/streaming.py
veritensor/core/types.py
veritensor/engines/__init__.py
veritensor/engines/hashing/__init__.py
veritensor/engines/hashing/calculator.py
veritensor/engines/hashing/lfs.py
veritensor/engines/hashing/readers.py
veritensor/engines/static/__init__.py
veritensor/engines/static/keras_engine.py
veritensor/engines/static/pickle_engine.py
veritensor/engines/static/rules.py
veritensor/engines/static/signatures.yaml
veritensor/integrations/__init__.py
veritensor/integrations/cosign.py
veritensor/integrations/huggingface.py
veritensor/reporting/sarif.py
veritensor/reporting/sbom.py
veritensor-1.2.2.dist-info/licenses/LICENSE
veritensor-1.2.2.dist-info/METADATA
veritensor-1.2.2.dist-info/WHEEL
veritensor-1.2.2.dist-info/entry_points.txt
veritensor-1.2.2.dist-info/top_level.txt
veritensor-1.2.2.dist-info/RECORD
