Metadata-Version: 2.4
Name: veritensor
Version: 1.2.2
Summary: Supply Chain Security for AI. Scans models (Pickle, PyTorch, Keras, GGUF) for malware and verifies integrity.
Author-email: Arsenii Brazhnyk <arsenii.brazhnyk@gmail.com>
License: Apache-2.0
Project-URL: Homepage, https://github.com/ArseniiBrazhnyk/Veritensor
Project-URL: Bug Tracker, https://github.com/ArseniiBrazhnyk/Veritensor/issues
Project-URL: Documentation, https://github.com/ArseniiBrazhnyk/Veritensor#readme
Keywords: security,ai,mlops,malware-detection,supply-chain,devsecops
Classifier: Development Status :: 4 - Beta
Classifier: Intended Audience :: Developers
Classifier: Intended Audience :: Science/Research
Classifier: Topic :: Security
Classifier: Topic :: Scientific/Engineering :: Artificial Intelligence
Classifier: License :: OSI Approved :: Apache Software License
Classifier: Programming Language :: Python :: 3
Classifier: Programming Language :: Python :: 3.10
Classifier: Programming Language :: Python :: 3.11
Classifier: Programming Language :: Python :: 3.12
Requires-Python: >=3.10
License-File: LICENSE
Requires-Dist: typer>=0.9.0
Requires-Dist: rich>=13.0.0
Requires-Dist: requests>=2.31.0
Requires-Dist: pyyaml>=6.0
Requires-Dist: huggingface_hub>=0.19.0
Requires-Dist: cyclonedx-python-lib>=6.0.0
Provides-Extra: test
Requires-Dist: pytest; extra == "test"
Requires-Dist: pytest-mock; extra == "test"
Requires-Dist: fickling>=0.0.1; extra == "test"
Dynamic: license-file
